happy_pandas/__init__.py
happy_pandas-0.3.dist-info/METADATA
happy_pandas-0.3.dist-info/WHEEL
happy_pandas-0.3.dist-info/top_level.txt
happy_pandas-0.3.dist-info/RECORD
