Metadata-Version: 2.1
Name: happy-pandas
Version: 0.3
Summary: UNKNOWN
Home-page: UNKNOWN
Author: voyager
Author-email: UNKNOWN
License: UNKNOWN
Platform: UNKNOWN
Requires-Dist: pandas
Requires-Dist: happybase
Requires-Dist: pyspark
